barkeep.cpython-310-x86_64-linux-gnu.so
.barkeep.mesonpy.libs/libfmt.so
barkeep-0.1.5.dist-info/RECORD
barkeep-0.1.5.dist-info/METADATA
barkeep-0.1.5.dist-info/WHEEL
barkeep-0.1.5.dist-info/LICENSE
