Metadata-Version: 2.1
Name: barkeep
Version: 0.1.5
Author: Ozan Irsoy
License:                                  Apache License
Requires-Python: >=3.9
